[
  {
      "code": "af",
      "country": "Afghanistan",
      "police": "119",
      "ambulance": "112",
      "fire": "119"
  },
  {
      "code": "al",
      "country": "Albania",
      "police": "129",
      "ambulance": "127",
      "fire": "128"
  },
  {
      "code": "dz",
      "country": "Algeria",
      "police": "1548",
      "ambulance": "14",
      "fire": "14"
  },
  {
      "code": "as",
      "country": "American Samoa",
      "police": "911",
      "ambulance": "911",
      "fire": "911"
  },
  {
      "code": "ad",
      "country": "Andorra",
      "police": "110",
      "ambulance": "116",
      "fire": "118"
  },
  {
      "code": "ao",
      "country": "Angola",
      "police": "113",
      "ambulance": "112",
      "fire": "115"
  },
  {
      "code": "ai",
      "country": "Anguilla",
      "police": "911",
      "ambulance": "911",
      "fire": "911"
  },
  {
      "code": "ag",
      "country": "Antigua and Barbuda",
      "police": "911 or 999",
      "ambulance": "911 or 999",
      "fire": "911 or 999"
  },
  {
      "code": "ar",
      "country": "Argentina",
      "police": "911",
      "ambulance": "911",
      "fire": "911"
  },
  {
      "code": "am",
      "country": "Armenia",
      "police": "112 or 911",
      "ambulance": "112 or 911",
      "fire": "112 or 911"
  },
  {
      "code": "aw",
      "country": "Aruba",
      "police": "911",
      "ambulance": "911",
      "fire": "911"
  },
  {
      "code": "au",
      "country": "Australia",
      "police": "000",
      "ambulance": "000",
      "fire": "000"
  },
  {
      "code": "at",
      "country": "Austria",
      "police": "112 or 133",
      "ambulance": "144",
      "fire": "122"
  },
  {
      "code": "az",
      "country": "Azerbaijan",
      "police": "102",
      "ambulance": "103",
      "fire": "101"
  },
  {
      "code": "bs",
      "country": "Bahamas",
      "police": "911 or 919",
      "ambulance": "911 or 919",
      "fire": "911 or 919"
  },
  {
      "code": "bh",
      "country": "Bahrain",
      "police": "999",
      "ambulance": "999",
      "fire": "999"
  },
  {
      "code": "bd",
      "country": "Bangladesh",
      "police": "999",
      "ambulance": "999",
      "fire": "999"
  },
  {
      "code": "bb",
      "country": "Barbados",
      "police": "911",
      "ambulance": "911",
      "fire": "911"
  },
  {
      "code": "by",
      "country": "Belarus",
      "police": "102",
      "ambulance": "103",
      "fire": "101"
  },
  {
      "code": "be",
      "country": "Belgium",
      "police": "101",
      "ambulance": "112",
      "fire": "112"
  },
  {
      "code": "bz",
      "country": "Belize",
      "police": "911",
      "ambulance": "911",
      "fire": "911"
  },
  {
      "code": "bj",
      "country": "Benin",
      "police": "117",
      "ambulance": "112",
      "fire": "118"
  },
  {
      "code": "bm",
      "country": "Bermuda",
      "police": "911",
      "ambulance": "911",
      "fire": "911"
  },
  {
      "code": "bt",
      "country": "Bhutan",
      "police": "113",
      "ambulance": "112",
      "fire": "110"
  },
  {
      "code": "bo",
      "country": "Bolivia",
      "police": "110",
      "ambulance": "118",
      "fire": "119"
  },
  {
      "code": "ba",
      "country": "Bosnia and Herzegovina",
      "police": "122",
      "ambulance": "124",
      "fire": "123"
  },
  {
      "code": "bw",
      "country": "Botswana",
      "police": "999",
      "ambulance": "997",
      "fire": "998"
  },
  {
      "code": "br",
      "country": "Brazil",
      "police": "190",
      "ambulance": "192",
      "fire": "193"
  },
  {
      "code":"vg",
      "country": "British Virgin Islands",
      "police": "911 or 999",
      "ambulance": "911 or 919",
      "fire": "911 or 919"
  },
  {
      "code": "bn",
      "country": "Brunei",
      "police": "993",
      "ambulance": "991",
      "fire": "995"
  },
  {
      "code": "bg",
      "country": "Bulgaria",
      "police": "112 or 166",
      "ambulance": "112 or 150",
      "fire": "112 or 160"
  },
  {
      "code": "bf",
      "country": "Burkina Faso",
      "police": "17",
      "ambulance": "112",
      "fire": "18"
  },
  {
      "code": "bi",
      "country": "Burundi",
      "police": "117",
      "ambulance": "112",
      "fire": "118"
  },
  {
      "code": "kh",
      "country": "Cambodia",
      "police": "117",
      "ambulance": "119",
      "fire": "118"
  },
  {
      "code": "cm",
      "country": "Cameroon",
      "police": "117",
      "ambulance": "119",
      "fire": "118"
  },
  {
      "code": "ca",
      "country": "Canada",
      "police": "911",
      "ambulance": "911",
      "fire": "911"
  },
  {
      "code": "cv",
      "country": "Cape Verde",
      "police": "132",
      "ambulance": "130",
      "fire": "131"
  },
  {
      "code": "ky",
      "country": "Cayman Islands",
      "police": "911",
      "ambulance": "911",
      "fire": "911"
  },
  {
      "code": "cf",
      "country": "Central African Republic",
      "police": "117",
      "ambulance": "1220",
      "fire": "118"
  },
  {
      "code": "td",
      "country": "Chad",
      "police": "17",
      "ambulance": "2251-4242",
      "fire": "18"
  },
  {
      "code": "cl",
      "country": "Chile",
      "police": "133",
      "ambulance": "131",
      "fire": "132"
  },
  {
      "code": "cn",
      "country": "China",
      "police": "110",
      "ambulance": "120",
      "fire": "119"
  },
  {
      "code": "co",
      "country": "Colombia",
      "police": "123",
      "ambulance": "123",
      "fire": "123"
  },
  {
      "code": "km",
      "country": "Comoros",
      "police": "17",
      "ambulance": "772-03-73",
      "fire": "18"
  },
  {
      "code": "ck",
      "country": "Cook Islands",
      "police": "999",
      "ambulance": "998",
      "fire": "996"
  },
  {
      "code": "cr",
      "country": "Costa Rica",
      "police": "911",
      "ambulance": "911",
      "fire": "911"
  },
  {
      "code": "hr",
      "country": "Croatia",
      "police": "192",
      "ambulance": "194",
      "fire": "193"
  },
  {
      "code": "cu",
      "country": "Cuba",
      "police": "106",
      "ambulance": "104",
      "fire": "105"
  },
  {
      "code": "cw",
      "country": "Curacao",
      "police": "911",
      "ambulance": "912",
      "fire": "911"
  },
  {
      "code": "cy",
      "country": "Cyprus",
      "police": "112 or 199",
      "ambulance": "112 or 199",
      "fire": "112 or 199"
  },
  {
      "code": "cz",
      "country": "Czech Republic",
      "police": "158",
      "ambulance": "155",
      "fire": "150"
  },
  {
      "code": "dk",
      "country": "Denmark",
      "police": "112",
      "ambulance": "112",
      "fire": "112"
  },
  {
      "code": "dj",
      "country": "Djibouti",
      "police": "17",
      "ambulance": "19",
      "fire": "18"
  },
  {
      "code": "dm",
      "country": "Dominica",
      "police": "999",
      "ambulance": "999",
      "fire": "999"
  },
  {
      "code": "do",
      "country": "Dominican Republic",
      "police": "911",
      "ambulance": "911",
      "fire": "911"
  },
  {
      "code": "cd",
      "country": "DR Congo",
      "police": "112",
      "ambulance": "118",
      "fire": "118"
  },
  {
      "code": "ec",
      "country": "Ecuador",
      "police": "911",
      "ambulance": "911",
      "fire": "911"
  },
  {
      "code": "eg",
      "country": "Egypt",
      "police": "122",
      "ambulance": "123",
      "fire": "180"
  },
  {
      "code": "sv",
      "country": "El Salvador",
      "police": "911",
      "ambulance": "132",
      "fire": "913"
  },
  {
      "code": "gq",
      "country": "Equatorial Guinea",
      "police": "114",
      "ambulance": "115",
      "fire": "112"
  },
  {
      "code": "er",
      "country": "Eritrea",
      "police": "113",
      "ambulance": "114",
      "fire": "116"
  },
  {
      "code": "ee",
      "country": "Estonia",
      "police": "112",
      "ambulance": "112",
      "fire": "112"
  },
  {
      "code": "sz",
      "country": "Eswatini",
      "police": "999",
      "ambulance": "977",
      "fire": "933"
  },
  {
      "code": "et",
      "country": "Ethiopia",
      "police": "911",
      "ambulance": "911",
      "fire": "911"
  },
  {
      "code": "fk",
      "country": "Falkland Islands",
      "police": "112 or 999",
      "ambulance": "112 or 999",
      "fire": "112 or 999"
  },
  {
      "code": "fo",
      "country": "Faroe Islands",
      "police": "112",
      "ambulance": "112",
      "fire": "112"
  },
  {
      "code": "fj",
      "country": "Fiji",
      "police": "911",
      "ambulance": "911",
      "fire": "911"
  },
  {
      "code": "fi",
      "country": "Finland",
      "police": "112",
      "ambulance": "112",
      "fire": "112"
  },
  {
      "code": "fr",
      "country": "France",
      "police": "17",
      "ambulance": "15",
      "fire": "18"
  },
  {
      "code": "gf",
      "country": "French Guiana",
      "police": "112",
      "ambulance": "112",
      "fire": "112"
  },
  {
      "code": "pf",
      "country": "French Polynesia",
      "police": "112",
      "ambulance": "112",
      "fire": "112"
  },
  {
      "code": "ga",
      "country": "Gabon",
      "police": "1730",
      "ambulance": "1300",
      "fire": "18"
  },
  {
      "code": "gm",
      "country": "Gambia",
      "police": "117",
      "ambulance": "116",
      "fire": "118"
  },
  {
      "code": "ge",
      "country": "Georgia",
      "police": "112",
      "ambulance": "112",
      "fire": "112"
  },
  {
      "code": "de",
      "country": "Germany",
      "police": "110",
      "ambulance": "112",
      "fire": "112"
  },
  {
      "code": "gh",
      "country": "Ghana",
      "police": "191",
      "ambulance": "193",
      "fire": "192"
  },
  {
      "code": "gi",
      "country": "Gibraltar",
      "police": "199 or 112 or 999",
      "ambulance": "190 or 112 or 999",
      "fire": "190 or 112 or 999"
  },
  {
      "code": "gr",
      "country": "Greece",
      "police": "100",
      "ambulance": "166",
      "fire": "199"
  },
  {
      "code": "gl",
      "country": "Greenland",
      "police": "112",
      "ambulance": "112",
      "fire": "112"
  },
  {
      "code": "gd",
      "country": "Grenada",
      "police": "911",
      "ambulance": "911",
      "fire": "911"
  },
  {
      "code": "gp",
      "country": "Guadeloupe",
      "police": "112",
      "ambulance": "112",
      "fire": "112"
  },
  {
      "code": "gu",
      "country": "Guam",
      "police": "911",
      "ambulance": "911",
      "fire": "911"
  },
  {
      "code": "gt",
      "country": "Guatemala",
      "police": "110",
      "ambulance": "128",
      "fire": "122"
  },
  {
      "code": "gg",
      "country": "Guernsey",
      "police": "112 or 999",
      "ambulance": "112 or 999",
      "fire": "112 or 999"
  },
  {
      "code": "gn",
      "country": "Guinea",
      "police": "117",
      "ambulance": "18",
      "fire": "442-020"
  },
  {
      "code": "gw",
      "country": "Guinea-Bissau",
      "police": "117",
      "ambulance": "119",
      "fire": "118"
  },
  {
      "code": "gy",
      "country": "Guyana",
      "police": "999",
      "ambulance": "999",
      "fire": "999"
  },
  {
      "code": "ht",
      "country": "Haiti",
      "police": "114",
      "ambulance": "116",
      "fire": "115"
  },
  {
      "code": "hn",
      "country": "Honduras",
      "police": "911",
      "ambulance": "195",
      "fire": "198"
  },
  {
      "code": "hk",
      "country": "Hong Kong",
      "police": "999",
      "ambulance": "999",
      "fire": "999"
  },
  {
      "code": "hu",
      "country": "Hungary",
      "police": "107",
      "ambulance": "104",
      "fire": "105"
  },
  {
      "code": "is",
      "country": "Iceland",
      "police": "112",
      "ambulance": "112",
      "fire": "112"
  },
  {
      "code": "in",
      "country": "India",
      "police": "112",
      "ambulance": "112",
      "fire": "112"
  },
  {
      "code": "id",
      "country": "Indonesia",
      "police": "112",
      "ambulance": "112",
      "fire": "112"
  },
  {
      "code": "ir",
      "country": "Iran",
      "police": "110",
      "ambulance": "115",
      "fire": "125"
  },
  {
      "code": "iq",
      "country": "Iraq",
      "police": "112",
      "ambulance": "122",
      "fire": "115"
  },
  {
      "code": "ie",
      "country": "Ireland",
      "police": "999 or 112",
      "ambulance": "999 or 112",
      "fire": "999 or 112"
  },
  {
      "code": "im",
      "country": "Isle of Man",
      "police": "112 or 999",
      "ambulance": "112 or 999",
      "fire": "112 or 999"
  },
  {
      "code": "il",
      "country": "Israel",
      "police": "100",
      "ambulance": "101",
      "fire": "102"
  },
  {
      "code": "it",
      "country": "Italy",
      "police": "112",
      "ambulance": "112",
      "fire": "112"
  },
  {
      "code": "cl",
      "country": "Ivory Coast",
      "police": "110 or 111 or 170",
      "ambulance": "185",
      "fire": "180"
  },
  {
      "code": "jm",
      "country": "Jamaica",
      "police": "119",
      "ambulance": "110",
      "fire": "110"
  },
  {
      "code": "jp",
      "country": "Japan",
      "police": "110",
      "ambulance": "119",
      "fire": "119"
  },
  {
      "code": "je",
      "country": "Jersey",
      "police": "112 or 999",
      "ambulance": "112 or 999",
      "fire": "112 or 999"
  },
  {
      "code": "jo",
      "country": "Jordan",
      "police": "911",
      "ambulance": "911",
      "fire": "911"
  },
  {
      "code": "kz",
      "country": "Kazakhstan",
      "police": "112",
      "ambulance": "112",
      "fire": "112"
  },
  {
      "code": "ke",
      "country": "Kenya",
      "police": "112 or 999 or 911",
      "ambulance": "112 or 999 or 911",
      "fire": "112 or 999 or 911"
  },
  {
      "code": "ki",
      "country": "Kiribati",
      "police": "999",
      "ambulance": "999",
      "fire": "999"
  },
  {
      "code": "kw",
      "country": "Kuwait",
      "police": "112",
      "ambulance": "112",
      "fire": "112"
  },
  {
      "code": "kg",
      "country": "Kyrgyzstan",
      "police": "102",
      "ambulance": "103",
      "fire": "101"
  },
  {
      "code": "la",
      "country": "Laos",
      "police": "191",
      "ambulance": "195",
      "fire": "190"
  },
  {
      "code": "lv",
      "country": "Latvia",
      "police": "112",
      "ambulance": "112",
      "fire": "112"
  },
  {
      "code": "lb",
      "country": "Lebanon",
      "police": "999 or 112",
      "ambulance": "140",
      "fire": "175"
  },
  {
      "code": "ls",
      "country": "Lesotho",
      "police": "123",
      "ambulance": "121",
      "fire": "122"
  },
  {
      "code": "lr",
      "country": "Liberia",
      "police": "911",
      "ambulance": "911",
      "fire": "911"
  },
  {
      "code": "ly",
      "country": "Libya",
      "police": "1515",
      "ambulance": "193",
      "fire": "1515"
  },
  {
      "code": "li",
      "country": "Liechtenstein",
      "police": "117",
      "ambulance": "144",
      "fire": "118"
  },
  {
      "code": "lt",
      "country": "Lithuania",
      "police": "112",
      "ambulance": "112",
      "fire": "112"
  },
  {
      "code": "lu",
      "country": "Luxembourg",
      "police": "112",
      "ambulance": "Police - 113.",
      "fire": "112"
  },
  {
      "code": "mo",
      "country": "Macau",
      "police": "999",
      "ambulance": "999",
      "fire": "999"
  },
  {
      "code": "mg",
      "country": "Madagascar",
      "police": "117",
      "ambulance": "124",
      "fire": "118"
  },
  {
      "code": "mw",
      "country": "Malawi",
      "police": "997",
      "ambulance": "998",
      "fire": "999"
  },
  {
      "code": "my",
      "country": "Malaysia",
      "police": "999",
      "ambulance": "994",
      "fire": "994"
  },
  {
      "code": "mv",
      "country": "Maldives",
      "police": "119",
      "ambulance": "102",
      "fire": "118"
  },
  {
      "code": "ml",
      "country": "Mali",
      "police": "17",
      "ambulance": "15",
      "fire": "18"
  },
  {
      "code": "mt",
      "country": "Malta",
      "police": "112",
      "ambulance": "112",
      "fire": "112"
  },
  {
      "code": "mh",
      "country": "Marshall Islands",
      "police": "911",
      "ambulance": "911",
      "fire": "911"
  },
  {
      "code": "mq",
      "country": "Martinique",
      "police": "112",
      "ambulance": "112",
      "fire": "112"
  },
  {
      "code": "mr",
      "country": "Mauritania",
      "police": "117",
      "ambulance": "101",
      "fire": "118"
  },
  {
      "code": "mu",
      "country": "Mauritius",
      "police": "112",
      "ambulance": "114",
      "fire": "115"
  },
  {
      "code": "yt",
      "country": "Mayotte",
      "police": "112",
      "ambulance": "112",
      "fire": "112"
  },
  {
      "code": "mx",
      "country": "Mexico",
      "police": "911",
      "ambulance": "911",
      "fire": "911"
  },
  {
      "code": "fm",
      "country": "Micronesia",
      "police": "911",
      "ambulance": "911",
      "fire": "911"
  },
  {
      "code": "md",
      "country": "Moldova",
      "police": "112",
      "ambulance": "112",
      "fire": "112"
  },
  {
      "code": "mc",
      "country": "Monaco",
      "police": "17",
      "ambulance": "15",
      "fire": "18"
  },
  {
      "code": "mn",
      "country": "Mongolia",
      "police": "105",
      "ambulance": "105",
      "fire": "105"
  },
  {
      "code": "me",
      "country": "Montenegro",
      "police": "122",
      "ambulance": "124",
      "fire": "123"
  },
  {
      "code": "ms",
      "country": "Montserrat",
      "police": "911 or 999",
      "ambulance": "911 or 919",
      "fire": "911 or 919"
  },
  {
      "code": "ma",
      "country": "Morocco",
      "police": "19",
      "ambulance": "15",
      "fire": "15"
  },
  {
      "code": "mz",
      "country": "Mozambique",
      "police": "119",
      "ambulance": "117",
      "fire": "198"
  },
  {
      "code": "mm",
      "country": "Myanmar",
      "police": "999",
      "ambulance": "999",
      "fire": "999"
  },
  {
      "code": "na",
      "country": "Namibia",
      "police": "10 111",
      "ambulance": "depends on town/city",
      "fire": "depends on town/city"
  },
  {
      "code": "nr",
      "country": "Nauru",
      "police": "110",
      "ambulance": "111",
      "fire": "112"
  },
  {
      "code": "np",
      "country": "Nepal",
      "police": "100",
      "ambulance": "102",
      "fire": "101"
  },
  {
      "code": "nl",
      "country": "Netherlands",
      "police": "112",
      "ambulance": "112",
      "fire": "112"
  },
  {
      "code": "nc",
      "country": "New Caledonia",
      "police": "112",
      "ambulance": "112",
      "fire": "112"
  },
  {
      "code": "nz",
      "country": "New Zealand",
      "police": "111",
      "ambulance": "111",
      "fire": "111"
  },
  {
      "code": "ni",
      "country": "Nicaragua",
      "police": "118",
      "ambulance": "128",
      "fire": "115"
  },
  {
      "code": "ne",
      "country": "Niger",
      "police": "17",
      "ambulance": "15",
      "fire": "18"
  },
  {
      "code": "ng",
      "country": "Nigeria",
      "police": "112",
      "ambulance": "112",
      "fire": "112"
  },
  {
      "code": "kp",
      "country": "North Korea",
      "police": "110",
      "ambulance": "119",
      "fire": "119"
  },
  {
      "code": "no",
      "country": "Norway",
      "police": "112",
      "ambulance": "113",
      "fire": "110"
  },
  {
      "code": "om",
      "country": "Oman",
      "police": "9999",
      "ambulance": "9999",
      "fire": "9999"
  },
  {
      "code": "pk",
      "country": "Pakistan",
      "police": "15",
      "ambulance": "115 and 1122",
      "fire": "16"
  },
  {
      "code": "pw",
      "country": "Palau",
      "police": "911",
      "ambulance": "911",
      "fire": "911"
  },
  {
      "code": "pa",
      "country": "Panama",
      "police": "911",
      "ambulance": "911",
      "fire": "911"
  },
  {
      "code": "pg",
      "country": "Papua New Guinea",
      "police": "112",
      "ambulance": "111",
      "fire": "110"
  },
  {
      "code": "py",
      "country": "Paraguay",
      "police": "911",
      "ambulance": "911",
      "fire": "911"
  },
  {
      "code": "pe",
      "country": "Peru",
      "police": "911",
      "ambulance": "911",
      "fire": "911"
  },
  {
      "code": "ph",
      "country": "Philippines",
      "police": "911",
      "ambulance": "911",
      "fire": "911"
  },
  {
      "code": "pl",
      "country": "Poland",
      "police": "997",
      "ambulance": "999",
      "fire": "998"
  },
  {
      "code": "pt",
      "country": "Portugal",
      "police": "112",
      "ambulance": "112",
      "fire": "112"
  },
  {
      "code": "pr",
      "country": "Puerto Rico",
      "police": "911",
      "ambulance": "911",
      "fire": "911"
  },
  {
      "code": "qa",
      "country": "Qatar",
      "police": "999",
      "ambulance": "999",
      "fire": "999"
  },
  {
      "code": "cg",
      "country": "Republic of the Congo",
      "police": "117",
      "ambulance": "118",
      "fire": "118"
  },
  {
      "code": "re",
      "country": "Reunion",
      "police": "112",
      "ambulance": "15",
      "fire": "18"
  },
  {
      "code": "ro",
      "country": "Romania",
      "police": "112",
      "ambulance": "112",
      "fire": "112"
  },
  {
      "code": "ru",
      "country": "Russia",
      "police": "102",
      "ambulance": "103",
      "fire": "101"
  },
  {
      "code": "rw",
      "country": "Rwanda",
      "police": "112",
      "ambulance": "912",
      "fire": "112"
  },
  {
      "code": "kn",
      "country": "Saint Kitts and Nevis",
      "police": "911",
      "ambulance": "911",
      "fire": "911"
  },
  {
      "code": "lc",
      "country": "Saint Lucia",
      "police": "911 or 999",
      "ambulance": "911 or 919",
      "fire": "911 or 919"
  },
  {
      "code": "pm",
      "country": "Saint Pierre and Miquelon",
      "police": "112",
      "ambulance": "112",
      "fire": "112"
  },
  {
      "code": "vc",
      "country": "Saint Vincent and the Grenadines",
      "police": "911 or 999",
      "ambulance": "911 or 919",
      "fire": "911 or 919"
  },
  {
      "code": "ws",
      "country": "Samoa",
      "police": "999",
      "ambulance": "999",
      "fire": "999"
  },
  {
      "code": "sm",
      "country": "San Marino",
      "police": "113",
      "ambulance": "118",
      "fire": "115"
  },
  {
      "code": "st",
      "country": "Sao Tome and Principe",
      "police": "112",
      "ambulance": "112",
      "fire": "112"
  },
  {
      "code": "sa",
      "country": "Saudi Arabia",
      "police": "911",
      "ambulance": "911",
      "fire": "911"
  },
  {
      "code": "sn",
      "country": "Senegal",
      "police": "17",
      "ambulance": "18",
      "fire": "1515"
  },
  {
      "code": "rs",
      "country": "Serbia",
      "police": "192 or 112",
      "ambulance": "194",
      "fire": "193"
  },
  {
      "code": "sc",
      "country": "Seychelles",
      "police": "112",
      "ambulance": "151",
      "fire": "112"
  },
  {
      "code": "sl",
      "country": "Sierra Leone",
      "police": "19",
      "ambulance": "999",
      "fire": "999"
  },
  {
      "code": "sg",
      "country": "Singapore",
      "police": "999",
      "ambulance": "995",
      "fire": "995"
  },
  {
      "code": "sk",
      "country": "Slovakia",
      "police": "158",
      "ambulance": "155",
      "fire": "150"
  },
  {
      "code": "si",
      "country": "Slovenia",
      "police": "112",
      "ambulance": "112",
      "fire": "112"
  },
  {
      "code": "sb",
      "country": "Solomon Islands",
      "police": "911 or 999",
      "ambulance": "911 or 999",
      "fire": "911 or 999"
  },
  {
      "code": "so",
      "country": "Somalia",
      "police": "888",
      "ambulance": "999",
      "fire": "555"
  },
  {
      "code": "za",
      "country": "South Africa",
      "police": "10 111",
      "ambulance": "10 177",
      "fire": "10 177"
  },
  {
      "code": "kr",
      "country": "South Korea",
      "police": "112",
      "ambulance": "119",
      "fire": "119"
  },
  {
      "code": "ss",
      "country": "South Sudan",
      "police": "999",
      "ambulance": "999",
      "fire": "999"
  },
  {
      "code": "es",
      "country": "Spain",
      "police": "112",
      "ambulance": "112",
      "fire": "112"
  },
  {
      "code": "lk",
      "country": "Sri Lanka",
      "police": "119",
      "ambulance": "110",
      "fire": "110"
  },
  {
      "code": "sd",
      "country": "Sudan",
      "police": "999",
      "ambulance": "Traffic police - 777 777.",
      "fire": "999"
  },
  {
      "code": "sr",
      "country": "Suriname",
      "police": "115",
      "ambulance": "115",
      "fire": "115"
  },
  {
      "code": "se",
      "country": "Sweden",
      "police": "112",
      "ambulance": "112",
      "fire": "112"
  },
  {
      "code": "ch",
      "country": "Switzerland",
      "police": "117",
      "ambulance": "144",
      "fire": "118"
  },
  {
      "code": "sy",
      "country": "Syria",
      "police": "112",
      "ambulance": "110",
      "fire": "113"
  },
  {
      "code": "tw",
      "country": "Taiwan",
      "police": "110",
      "ambulance": "119",
      "fire": "119"
  },
  {
      "code": "tj",
      "country": "Tajikistan",
      "police": "112",
      "ambulance": "112",
      "fire": "112"
  },
  {
      "code": "tz",
      "country": "Tanzania",
      "police": "112",
      "ambulance": "114",
      "fire": "115"
  },
  {
      "code": "th",
      "country": "Thailand",
      "police": "191 or 911",
      "ambulance": "1669",
      "fire": "199"
  },
  {
      "code": "tl",
      "country": "Timor-Leste",
      "police": "112",
      "ambulance": "112",
      "fire": "112"
  },
  {
      "code": "tg",
      "country": "Togo",
      "police": "117",
      "ambulance": "8200",
      "fire": "118"
  },
  {
      "code": "to",
      "country": "Tonga",
      "police": "911",
      "ambulance": "911",
      "fire": "911"
  },
  {
      "code": "tt",
      "country": "Trinidad and Tobago",
      "police": "999 or 911",
      "ambulance": "811",
      "fire": "990"
  },
  {
      "code": "tn",
      "country": "Tunisia",
      "police": "197",
      "ambulance": "198",
      "fire": "190"
  },
  {
      "code": "tr",
      "country": "Turkey",
      "police": "112",
      "ambulance": "112",
      "fire": "112"
  },
  {
      "code": "tm",
      "country": "Turkmenistan",
      "police": "112",
      "ambulance": "112",
      "fire": "112"
  },
  {
      "code": "tv",
      "country": "Tuvalu",
      "police": "911",
      "ambulance": "911",
      "fire": "911"
  },
  {
      "code": "ug",
      "country": "Uganda",
      "police": "112",
      "ambulance": "911",
      "fire": "112"
  },
  {
      "code": "ae",
      "country": "United Arab Emirates",
      "police": "999",
      "ambulance": "999",
      "fire": "999"
  },
  {
      "code": "gb",
      "country": "United Kingdom",
      "police": "999 or 112",
      "ambulance": "999 or 112",
      "fire": "999 or 112"
  },
  {
      "code": "us",
      "country": "United States",
      "police": "911",
      "ambulance": "911",
      "fire": "911"
  },
  {
      "code": "vi",
      "country": "United States Virgin Islands",
      "police": "911",
      "ambulance": "911",
      "fire": "911"
  },
  {
      "code": "uy",
      "country": "Uruguay",
      "police": "911",
      "ambulance": "911",
      "fire": "911"
  },
  {
      "code": "uz",
      "country": "Uzbekistan",
      "police": "102",
      "ambulance": "101",
      "fire": "103"
  },
  {
      "code": "vu",
      "country": "Vanuatu",
      "police": "112",
      "ambulance": "911",
      "fire": "911"
  },
  {
      "code": "va",
      "country": "Vatican City",
      "police": "112",
      "ambulance": "112",
      "fire": "112"
  },
  {
      "code": "ve",
      "country": "Venezuela",
      "police": "911 and 171",
      "ambulance": "911 and 171",
      "fire": "911 and 171"
  },
  {
      "code": "vn",
      "country": "Vietnam",
      "police": "113",
      "ambulance": "115",
      "fire": "114"
  },
  {
      "code": "eh",
      "country": "Western Sahara",
      "police": "150",
      "ambulance": "150",
      "fire": "150"
  },
  {
      "code": "ye",
      "country": "Yemen",
      "police": "194",
      "ambulance": "191",
      "fire": "191"
  },
  {
      "code": "zm",
      "country": "Zambia",
      "police": "999",
      "ambulance": "992",
      "fire": "993"
  },
  {
      "code": "zw",
      "country": "Zimbabwe",
      "police": "999",
      "ambulance": "994",
      "fire": "993"
  }
]